SMC/__init__.py
SMC/main.py
Scratch_Messaging_Client-3.0.dist-info/LICENSE
Scratch_Messaging_Client-3.0.dist-info/METADATA
Scratch_Messaging_Client-3.0.dist-info/WHEEL
Scratch_Messaging_Client-3.0.dist-info/entry_points.txt
Scratch_Messaging_Client-3.0.dist-info/top_level.txt
Scratch_Messaging_Client-3.0.dist-info/RECORD
