Metadata-Version: 2.1
Name: Scratch-Messaging-Client
Version: 3.0
License-File: LICENSE
Requires-Dist: scratchattach
